{
  "url": "https://api.github.com/repos/crownengine/crown/releases/210217133",
  "assets_url": "https://api.github.com/repos/crownengine/crown/releases/210217133/assets",
  "upload_url": "https://uploads.github.com/repos/crownengine/crown/releases/210217133/assets{?name,label}",
  "html_url": "https://github.com/crownengine/crown/releases/tag/v0.55.0",
  "id": 210217133,
  "author": {
    "login": "dbartolini",
    "id": 2070946,
    "node_id": "MDQ6VXNlcjIwNzA5NDY=",
    "avatar_url": "https://avatars.githubusercontent.com/u/2070946?v=4",
    "gravatar_id": "",
    "url": "https://api.github.com/users/dbartolini",
    "html_url": "https://github.com/dbartolini",
    "followers_url": "https://api.github.com/users/dbartolini/followers",
    "following_url": "https://api.github.com/users/dbartolini/following{/other_user}",
    "gists_url": "https://api.github.com/users/dbartolini/gists{/gist_id}",
    "starred_url": "https://api.github.com/users/dbartolini/starred{/owner}{/repo}",
    "subscriptions_url": "https://api.github.com/users/dbartolini/subscriptions",
    "organizations_url": "https://api.github.com/users/dbartolini/orgs",
    "repos_url": "https://api.github.com/users/dbartolini/repos",
    "events_url": "https://api.github.com/users/dbartolini/events{/privacy}",
    "received_events_url": "https://api.github.com/users/dbartolini/received_events",
    "type": "User",
    "user_view_type": "public",
    "site_admin": false
  },
  "node_id": "RE_kwDOAFEyY84Mh6it",
  "tag_name": "v0.55.0",
  "target_commitish": "master",
  "name": "",
  "draft": false,
  "prerelease": false,
  "created_at": "2025-04-03T18:59:58Z",
  "published_at": "2025-04-03T22:12:17Z",
  "assets": [
    {
      "url": "https://api.github.com/repos/crownengine/crown/releases/assets/243318946",
      "id": 243318946,
      "node_id": "RA_kwDOAFEyY84OgMCi",
      "name": "crown-0.55.0-linux-x64.tar.gz",
      "label": null,
      "uploader": {
        "login": "dbartolini",
        "id": 2070946,
        "node_id": "MDQ6VXNlcjIwNzA5NDY=",
        "avatar_url": "https://avatars.githubusercontent.com/u/2070946?v=4",
        "gravatar_id": "",
        "url": "https://api.github.com/users/dbartolini",
        "html_url": "https://github.com/dbartolini",
        "followers_url": "https://api.github.com/users/dbartolini/followers",
        "following_url": "https://api.github.com/users/dbartolini/following{/other_user}",
        "gists_url": "https://api.github.com/users/dbartolini/gists{/gist_id}",
        "starred_url": "https://api.github.com/users/dbartolini/starred{/owner}{/repo}",
        "subscriptions_url": "https://api.github.com/users/dbartolini/subscriptions",
        "organizations_url": "https://api.github.com/users/dbartolini/orgs",
        "repos_url": "https://api.github.com/users/dbartolini/repos",
        "events_url": "https://api.github.com/users/dbartolini/events{/privacy}",
        "received_events_url": "https://api.github.com/users/dbartolini/received_events",
        "type": "User",
        "user_view_type": "public",
        "site_admin": false
      },
      "content_type": "application/gzip",
      "state": "uploaded",
      "size": 55341328,
      "download_count": 0,
      "created_at": "2025-04-03T20:36:28Z",
      "updated_at": "2025-04-03T20:36:34Z",
      "browser_download_url": "https://github.com/crownengine/crown/releases/download/v0.55.0/crown-0.55.0-linux-x64.tar.gz"
    },
    {
      "url": "https://api.github.com/repos/crownengine/crown/releases/assets/243318970",
      "id": 243318970,
      "node_id": "RA_kwDOAFEyY84OgMC6",
      "name": "crown-0.55.0-windows-x64.zip",
      "label": null,
      "uploader": {
        "login": "dbartolini",
        "id": 2070946,
        "node_id": "MDQ6VXNlcjIwNzA5NDY=",
        "avatar_url": "https://avatars.githubusercontent.com/u/2070946?v=4",
        "gravatar_id": "",
        "url": "https://api.github.com/users/dbartolini",
        "html_url": "https://github.com/dbartolini",
        "followers_url": "https://api.github.com/users/dbartolini/followers",
        "following_url": "https://api.github.com/users/dbartolini/following{/other_user}",
        "gists_url": "https://api.github.com/users/dbartolini/gists{/gist_id}",
        "starred_url": "https://api.github.com/users/dbartolini/starred{/owner}{/repo}",
        "subscriptions_url": "https://api.github.com/users/dbartolini/subscriptions",
        "organizations_url": "https://api.github.com/users/dbartolini/orgs",
        "repos_url": "https://api.github.com/users/dbartolini/repos",
        "events_url": "https://api.github.com/users/dbartolini/events{/privacy}",
        "received_events_url": "https://api.github.com/users/dbartolini/received_events",
        "type": "User",
        "user_view_type": "public",
        "site_admin": false
      },
      "content_type": "application/zip",
      "state": "uploaded",
      "size": 92030668,
      "download_count": 0,
      "created_at": "2025-04-03T20:36:34Z",
      "updated_at": "2025-04-03T20:36:40Z",
      "browser_download_url": "https://github.com/crownengine/crown/releases/download/v0.55.0/crown-0.55.0-windows-x64.zip"
    },
    {
      "url": "https://api.github.com/repos/crownengine/crown/releases/assets/243318990",
      "id": 243318990,
      "node_id": "RA_kwDOAFEyY84OgMDO",
      "name": "SHA256SUMS",
      "label": null,
      "uploader": {
        "login": "dbartolini",
        "id": 2070946,
        "node_id": "MDQ6VXNlcjIwNzA5NDY=",
        "avatar_url": "https://avatars.githubusercontent.com/u/2070946?v=4",
        "gravatar_id": "",
        "url": "https://api.github.com/users/dbartolini",
        "html_url": "https://github.com/dbartolini",
        "followers_url": "https://api.github.com/users/dbartolini/followers",
        "following_url": "https://api.github.com/users/dbartolini/following{/other_user}",
        "gists_url": "https://api.github.com/users/dbartolini/gists{/gist_id}",
        "starred_url": "https://api.github.com/users/dbartolini/starred{/owner}{/repo}",
        "subscriptions_url": "https://api.github.com/users/dbartolini/subscriptions",
        "organizations_url": "https://api.github.com/users/dbartolini/orgs",
        "repos_url": "https://api.github.com/users/dbartolini/repos",
        "events_url": "https://api.github.com/users/dbartolini/events{/privacy}",
        "received_events_url": "https://api.github.com/users/dbartolini/received_events",
        "type": "User",
        "user_view_type": "public",
        "site_admin": false
      },
      "content_type": "application/octet-stream",
      "state": "uploaded",
      "size": 191,
      "download_count": 0,
      "created_at": "2025-04-03T20:36:40Z",
      "updated_at": "2025-04-03T20:36:40Z",
      "browser_download_url": "https://github.com/crownengine/crown/releases/download/v0.55.0/SHA256SUMS"
    }
  ],
  "tarball_url": "https://api.github.com/repos/crownengine/crown/tarball/v0.55.0",
  "zipball_url": "https://api.github.com/repos/crownengine/crown/zipball/v0.55.0",
  "body": "Crown v0.55 is out with PBR rendering, FBX skeleton/animation importing, shader and material hot-reloading, new Lua APIs, and tons of fixes:\r\n\r\n:scroll: [Changelog](https://docs.crownengine.org/html/latest/changelog.html#apr-2025)\r\n:floppy_disk: [Download](https://crownengine.org/download)\r\n:heart: [Donate](https://crownengine.org/fund)\r\n\r\n![0 54](https://github.com/user-attachments/assets/1a165045-df0c-4007-9951-e29250c7ed5c)"
}
